hepdata_cli/__init__.py
hepdata_cli/api.py
hepdata_cli/cli.py
hepdata_cli/resilient_requests.py
hepdata_cli/version.py
hepdata_cli-0.3.1.dist-info/licenses/LICENSE.txt
hepdata_cli-0.3.1.dist-info/METADATA
hepdata_cli-0.3.1.dist-info/WHEEL
hepdata_cli-0.3.1.dist-info/entry_points.txt
hepdata_cli-0.3.1.dist-info/top_level.txt
hepdata_cli-0.3.1.dist-info/RECORD
