Metadata-Version: 2.4
Name: hepdata-cli
Version: 0.3.1
Summary: CLI and API to allow users to search, download from and upload to HEPData
Home-page: https://github.com/HEPData/hepdata-cli
Author: Giuseppe De Laurentis
Author-email: g.dl@hotmail.it
License: GPLv3
Keywords: hepdata cli api
Platform: any
Requires-Python: >=3.7
License-File: LICENSE.txt
Requires-Dist: click
Requires-Dist: requests
Provides-Extra: tests
Requires-Dist: pytest; extra == "tests"
Requires-Dist: pytest-cov; extra == "tests"
Requires-Dist: requests_mock; extra == "tests"
Dynamic: author
Dynamic: author-email
Dynamic: home-page
Dynamic: keywords
Dynamic: license
Dynamic: license-file
Dynamic: platform
Dynamic: provides-extra
Dynamic: requires-dist
Dynamic: requires-python
Dynamic: summary
